wai/__init__.py
wai/__main__.py
wai/version.py
wai_client-0.1.2.dist-info/LICENSE
wai_client-0.1.2.dist-info/METADATA
wai_client-0.1.2.dist-info/WHEEL
wai_client-0.1.2.dist-info/entry_points.txt
wai_client-0.1.2.dist-info/top_level.txt
wai_client-0.1.2.dist-info/RECORD
