Metadata-Version: 2.1
Name: wai-client
Version: 0.1.2
Summary: Wai client app
Home-page: https://p0nk.net/wai
Author: dlek
Author-email: dlek@p0nk.net
License: MIT license
Project-URL: Source, https://gitlab.com/dlek/wai-client
Project-URL: Tracker, https://gitlab.com/dlek/wai-client/issues
Requires-Python: >=3.6
License-File: LICENSE
Requires-Dist: requests
Requires-Dist: toga (>=v0.3.0dev32)
Requires-Dist: emoji
